furiosa_native_device-0.2.2.dist-info/METADATA
furiosa_native_device-0.2.2.dist-info/WHEEL
furiosa_native_device/__init__.py
furiosa_native_device/furiosa_native_device.cpython-39-x86_64-linux-gnu.so
furiosa_native_device-0.2.2.dist-info/RECORD
