Metadata-Version: 2.1
Name: furiosa-native-device
Version: 0.2.2
Classifier: Programming Language :: Rust
Classifier: Programming Language :: Python :: Implementation :: CPython
Classifier: Programming Language :: Python :: Implementation :: PyPy
Requires-Dist: pytest ~=7.3 ; extra == 'test'
Requires-Dist: pytest-asyncio ~=0.21 ; extra == 'test'
Provides-Extra: test
Requires-Python: >=3.8
